alm.cpython-39-darwin.so
alm_pkg/__init__.py
anyks_lm-3.5.0.data/data/include/alm/ablm.hpp
anyks_lm-3.5.0.data/data/include/alm/alm.hpp
anyks_lm-3.5.0.data/data/include/alm/alphabet.hpp
anyks_lm-3.5.0.data/data/include/alm/arpa.hpp
anyks_lm-3.5.0.data/data/include/alm/aspl.hpp
anyks_lm-3.5.0.data/data/include/alm/collector.hpp
anyks_lm-3.5.0.data/data/include/alm/env.hpp
anyks_lm-3.5.0.data/data/include/alm/fsys.hpp
anyks_lm-3.5.0.data/data/include/alm/idw.hpp
anyks_lm-3.5.0.data/data/include/alm/levenshtein.hpp
anyks_lm-3.5.0.data/data/include/alm/nwt.hpp
anyks_lm-3.5.0.data/data/include/alm/progress.hpp
anyks_lm-3.5.0.data/data/include/alm/python.hpp
anyks_lm-3.5.0.data/data/include/alm/threadpool.hpp
anyks_lm-3.5.0.data/data/include/alm/tokenizer.hpp
anyks_lm-3.5.0.data/data/include/alm/toolkit.hpp
anyks_lm-3.5.0.data/data/include/alm/word.hpp
anyks_lm-3.5.0.data/data/include/alm/app/alm.hpp
anyks_lm-3.5.0.data/data/include/bigint/BigInteger.hh
anyks_lm-3.5.0.data/data/include/bigint/BigIntegerAlgorithms.hh
anyks_lm-3.5.0.data/data/include/bigint/BigIntegerLibrary.hh
anyks_lm-3.5.0.data/data/include/bigint/BigIntegerUtils.hh
anyks_lm-3.5.0.data/data/include/bigint/BigUnsigned.hh
anyks_lm-3.5.0.data/data/include/bigint/BigUnsignedInABase.hh
anyks_lm-3.5.0.data/data/include/bigint/NumberlikeArray.hh
anyks_lm-3.5.0.data/data/include/cityhash/city.h
anyks_lm-3.5.0.data/data/include/cityhash/citycrc.h
anyks_lm-3.5.0.data/data/include/cityhash/config.h
anyks_lm-3.5.0.data/data/include/nlohmann/json.hpp
anyks_lm-3.5.0.dist-info/LICENSE
anyks_lm-3.5.0.dist-info/METADATA
anyks_lm-3.5.0.dist-info/WHEEL
anyks_lm-3.5.0.dist-info/top_level.txt
anyks_lm-3.5.0.dist-info/RECORD
